spherely.cpython-312-darwin.so
spherely.pyi
spherely.dylibs/libs2geography.dylib
spherely.dylibs/libssl.3.dylib
spherely.dylibs/libcrypto.3.dylib
spherely.dylibs/libs2.0.11.1.dylib
spherely-0.0.1.dist-info/RECORD
spherely-0.0.1.dist-info/WHEEL
spherely-0.0.1.dist-info/METADATA
spherely-0.0.1.dist-info/licenses/LICENSE
spherely-0.0.1.dist-info/licenses/LICENSE_absl.txt
spherely-0.0.1.dist-info/licenses/LICENSE_s2geography.md
spherely-0.0.1.dist-info/licenses/LICENSE_s2geometry.txt
spherely-0.0.1.dist-info/licenses/LICENSE_openssl.txt
