Metadata-Version: 2.1
Name: spherely
Version: 0.0.1
Summary: Manipulation and analysis of geometric objects on the sphere
Keywords: gis,geometry,s2geometry,shapely
Author: Benoît Bovy
Maintainer: Spherely contributors
License: BSD 3-Clause
Project-URL: Home, https://spherely.readthedocs.io
Project-URL: Repository, https://github.com/benbovy/spherely
Requires-Python: >=3.10
Requires-Dist: numpy
Requires-Dist: pytest>=6.0; extra == "test"
Provides-Extra: test
